{
    "telize:6:0": [
        "SC-SET",
        "SC-SET-F-X"
    ],
    "telize:6:1": [
        "SC-MKDIR",
        "SC-MKDIR-PATHS",
        "SC-MKDIR-PATH",
        "ABS-PATH-ABSOLUTE",
        "SC-MKDIR",
        "SC-MKDIR-PATHS",
        "SC-MKDIR-PATH",
        "ABS-MAYBE-PATH"
    ],
    "telize:6:2": [
        "SC-CURL",
        "SC-CURL-F-SHOW-ERROR",
        "SC-CURL",
        "SC-CURL-F-LOCATION",
        "SC-CURL",
        "SC-CURL-URL",
        "ABS-URL-PROTOCOL-HTTPS",
        "SC-CURL",
        "SC-CURL-URL",
        "ABS-PROBABLY-URL"
    ],
    "telize:6:3": [
        "SC-TAR",
        "SC-TAR-Z",
        "SC-TAR",
        "SC-TAR-FILE",
        "SC-TAR",
        "SC-TAR-STRIP-COMPONENTS",
        "SC-TAR",
        "SC-TAR-DIRECTORY",
        "ABS-PATH-ABSOLUTE",
        "SC-TAR",
        "SC-TAR-DIRECTORY",
        "ABS-MAYBE-PATH"
    ],
    "telize:6:4": [
        "SC-CURL",
        "SC-CURL-F-SHOW-ERROR",
        "SC-CURL",
        "SC-CURL-F-LOCATION",
        "SC-CURL",
        "SC-CURL-URL",
        "ABS-URL-PROTOCOL-HTTPS",
        "SC-CURL",
        "SC-CURL-URL",
        "ABS-PROBABLY-URL"
    ],
    "telize:6:5": [
        "SC-TAR",
        "SC-TAR-Z",
        "SC-TAR",
        "SC-TAR-FILE",
        "SC-TAR",
        "SC-TAR-STRIP-COMPONENTS",
        "SC-TAR",
        "SC-TAR-DIRECTORY",
        "ABS-PATH-ABSOLUTE",
        "SC-TAR",
        "SC-TAR-DIRECTORY",
        "ABS-MAYBE-PATH"
    ],
    "telize:6:6": [
        "SC-CURL",
        "SC-CURL-F-SHOW-ERROR",
        "SC-CURL",
        "SC-CURL-F-LOCATION",
        "SC-CURL",
        "SC-CURL-URL",
        "ABS-URL-PROTOCOL-HTTPS",
        "SC-CURL",
        "SC-CURL-URL",
        "ABS-PROBABLY-URL"
    ],
    "telize:6:7": [
        "SC-TAR",
        "SC-TAR-Z",
        "SC-TAR",
        "SC-TAR-FILE",
        "SC-TAR",
        "SC-TAR-STRIP-COMPONENTS",
        "SC-TAR",
        "SC-TAR-DIRECTORY",
        "ABS-PATH-ABSOLUTE",
        "SC-TAR",
        "SC-TAR-DIRECTORY",
        "ABS-MAYBE-PATH"
    ],
    "telize:6:8": [
        "SC-GIT-CLONE",
        "SC-GIT-URL",
        "ABS-PROBABLY-URL",
        "SC-GIT-CLONE",
        "SC-GIT-DIRECTORY",
        "ABS-PATH-ABSOLUTE",
        "SC-GIT-CLONE",
        "SC-GIT-DIRECTORY",
        "ABS-MAYBE-SRC-DIR",
        "SC-GIT-CLONE",
        "SC-GIT-DIRECTORY",
        "ABS-USR-SRC-DIR",
        "SC-GIT-CLONE",
        "SC-GIT-DIRECTORY",
        "ABS-MAYBE-PATH"
    ],
    "telize:6:9": [
        "SC-CD",
        "SC-CD-PATH",
        "ABS-MAYBE-SRC-DIR",
        "SC-CD",
        "SC-CD-PATH",
        "ABS-USR-SRC-DIR",
        "SC-CD",
        "SC-CD-PATH",
        "ABS-MAYBE-PATH"
    ],
    "telize:6:10": [
        "SC-CP",
        "SC-CP-PATHS",
        "SC-CP-PATH",
        "SC-CP",
        "SC-CP-PATHS",
        "SC-CP-PATH",
        "ABS-PATH-ABSOLUTE",
        "SC-CP",
        "SC-CP-PATHS",
        "SC-CP-PATH",
        "ABS-MAYBE-PATH"
    ]
}